vegafusion_jupyter/__init__.py
vegafusion_jupyter/_frontend.py
vegafusion_jupyter/_version.py
vegafusion_jupyter/renderer.py
vegafusion_jupyter/widget.py
vegafusion_jupyter/labextension/package.json
vegafusion_jupyter/labextension/static/340.8000ebc41a0ba6fcde8b.js
vegafusion_jupyter/labextension/static/342.c243a8fb40dc86a962ad.js
vegafusion_jupyter/labextension/static/342.c243a8fb40dc86a962ad.js.LICENSE.txt
vegafusion_jupyter/labextension/static/375.38501ef62689b798bf23.js
vegafusion_jupyter/labextension/static/42.7f340c1b888746330122.js
vegafusion_jupyter/labextension/static/439.66cc935afb7e9bf3bdb9.js
vegafusion_jupyter/labextension/static/473.5b7ac7122ca6b5266956.js
vegafusion_jupyter/labextension/static/480.1bbfa387a4decef0a812.js
vegafusion_jupyter/labextension/static/568.b5d5c42737fb11426cd0.js
vegafusion_jupyter/labextension/static/65.0dd9c8c0248959a369ec.js
vegafusion_jupyter/labextension/static/877.7ffe35efa35ba56ae85a.js
vegafusion_jupyter/labextension/static/936.5fd0d5501f212f8ac14e.js
vegafusion_jupyter/labextension/static/efe94fb19af9c243d85a.module.wasm
vegafusion_jupyter/labextension/static/remoteEntry.309c24c3ed6d290e29ab.js
vegafusion_jupyter/labextension/static/style.js
vegafusion_jupyter/labextension/static/third-party-licenses.json
vegafusion_jupyter/nbextension/09b0955a7972d6bf2939.module.wasm
vegafusion_jupyter/nbextension/349.index.js
vegafusion_jupyter/nbextension/349.index.js.LICENSE.txt
vegafusion_jupyter/nbextension/562.index.js
vegafusion_jupyter/nbextension/594.index.js
vegafusion_jupyter/nbextension/876.index.js
vegafusion_jupyter/nbextension/extension.js
vegafusion_jupyter/nbextension/index.js
vegafusion_jupyter-1.6.9.data/data/etc/jupyter/nbconfig/notebook.d/vegafusion-jupyter.json
vegafusion_jupyter-1.6.9.data/data/share/jupyter/labextensions/vegafusion-jupyter/install.json
vegafusion_jupyter-1.6.9.data/data/share/jupyter/labextensions/vegafusion-jupyter/package.json
vegafusion_jupyter-1.6.9.dist-info/METADATA
vegafusion_jupyter-1.6.9.dist-info/WHEEL
vegafusion_jupyter-1.6.9.dist-info/top_level.txt
vegafusion_jupyter-1.6.9.dist-info/RECORD
