Metadata-Version: 2.1
Name: vegafusion-jupyter
Version: 1.6.9
Summary: Altair Jupyter Widget library that relies on VegaFusion for serverside calculations
Home-page: https://vegafusion.io
Author: Jon Mease
Author-email: jonmmease@gmail.com
License: BSD-3-Clause
Keywords: Jupyter,Widgets,IPython
Platform: Linux
Platform: Mac OS X
Platform: Windows
Classifier: Intended Audience :: Developers
Classifier: Intended Audience :: Science/Research
Classifier: License :: OSI Approved :: BSD License
Classifier: Programming Language :: Python
Classifier: Programming Language :: Python :: 3
Classifier: Programming Language :: Python :: 3.7
Classifier: Programming Language :: Python :: 3.8
Classifier: Programming Language :: Python :: 3.9
Classifier: Programming Language :: Python :: 3.10
Classifier: Framework :: Jupyter
Requires-Python: >=3.7
Requires-Dist: ipywidgets <9,>=7.0.0
Requires-Dist: altair >=4.2.0
Requires-Dist: vegafusion ==1.6.9
Provides-Extra: embed
Requires-Dist: vegafusion-python-embed ==1.6.9 ; extra == 'embed'
Requires-Dist: vl-convert-python >=0.7.0 ; extra == 'embed'
